terrajinja/sbp/commvault/data_commvault_client.py
terrajinja/sbp/commvault/data_commvault_plan.py
terrajinja/sbp/commvault/kubernetes_cluster.py
terrajinja/sbp/commvault/plan_backupdestination.py
terrajinja_sbp_commvault-0.2.0.dist-info/LICENSE
terrajinja_sbp_commvault-0.2.0.dist-info/METADATA
terrajinja_sbp_commvault-0.2.0.dist-info/WHEEL
terrajinja_sbp_commvault-0.2.0.dist-info/top_level.txt
terrajinja_sbp_commvault-0.2.0.dist-info/RECORD
